koornwinder/__about__.py
koornwinder/__init__.py
koornwinder/_koornwinder.py
koornwinder/koornwinder.json
koornwinder-0.0.2.dist-info/METADATA
koornwinder-0.0.2.dist-info/WHEEL
koornwinder-0.0.2.dist-info/RECORD
